{
  "questions": [
    {
      "question": "When you hovered over a hospital, was the location information represented as an address or latitude, longitude coordinate?",
      "options": [
        {
          "answer": "Address",
          "key": 1
        },
        {
          "answer": "Latitude, longitude coordinate",
          "key": 2
        }
      ],
      "correctAnswer": 1
    },
    {
      "question": "When you hovered over a ward, was the size represented as a length, area, or volume?",
      "options": [
        {
          "answer": "Length",
          "key": 1
        },
        {
          "answer": "Area",
          "key": 2
        },
        {
          "answer": "Volume",
          "key": 3
        }
      ],
      "correctAnswer": 2
    },
    {
      "question": "When you hovered over a highway, was the size represented as a length, area, or volume?",
      "options": [
        {
          "answer": "Length",
          "key": 1
        },
        {
          "answer": "Area",
          "key": 2
        },
        {
          "answer": "Volume",
          "key": 3
        }
      ],
      "correctAnswer": 1
    },
    {
      "question": "The Hospitals dataset possesses which mark and channels?",
      "options": [
        {
          "answer": "Point, Position, Color, and Shape",
          "key": 1
        },
        {
          "answer": "Point, Position, Color, Tilt, and Shape",
          "key": 2
        },
        {
          "answer": "Point, Position, Color, Tilt, Area, and Shape",
          "key": 3
        }
      ],
      "correctAnswer": 1
    },
    {
      "question": "Though a hospital could change in shape an infinite number of times, how many shape styles did you count in the Visually Encoded Map? (on desktop browsers)",
      "options": [
        {
          "answer": "6",
          "key": 1
        },
        {
          "answer": "3",
          "key": 2
        },
        {
          "answer": "2",
          "key": 3
        },
        {
          "answer": "4",
          "key": 4
        }
      ],
      "correctAnswer": 4
    }
  ]
}
